maestro/__init__.py
maestro/cli/__init__.py
maestro/cli/env.py
maestro/cli/introspection.py
maestro/cli/main.py
maestro/cli/utils.py
maestro/trainer/__init__.py
maestro/trainer/common/__init__.py
maestro/trainer/common/callbacks.py
maestro/trainer/common/datasets.py
maestro/trainer/common/env.py
maestro/trainer/common/metrics.py
maestro/trainer/common/training.py
maestro/trainer/common/utils/__init__.py
maestro/trainer/common/utils/device.py
maestro/trainer/common/utils/path.py
maestro/trainer/common/utils/seed.py
maestro/trainer/models/__init__.py
maestro/trainer/models/florence_2/__init__.py
maestro/trainer/models/florence_2/checkpoints.py
maestro/trainer/models/florence_2/core.py
maestro/trainer/models/florence_2/entrypoint.py
maestro/trainer/models/florence_2/inference.py
maestro/trainer/models/florence_2/loaders.py
maestro/trainer/models/paligemma_2/__init__.py
maestro/trainer/models/paligemma_2/checkpoints.py
maestro/trainer/models/paligemma_2/core.py
maestro/trainer/models/paligemma_2/entrypoint.py
maestro/trainer/models/paligemma_2/inference.py
maestro/trainer/models/paligemma_2/loaders.py
maestro/trainer/models/qwen_2_5_vl/__init__.py
maestro/trainer/models/qwen_2_5_vl/checkpoints.py
maestro/trainer/models/qwen_2_5_vl/core.py
maestro/trainer/models/qwen_2_5_vl/entrypoint.py
maestro/trainer/models/qwen_2_5_vl/inference.py
maestro/trainer/models/qwen_2_5_vl/loaders.py
maestro-1.0.0.dist-info/LICENSE
maestro-1.0.0.dist-info/METADATA
maestro-1.0.0.dist-info/WHEEL
maestro-1.0.0.dist-info/entry_points.txt
maestro-1.0.0.dist-info/top_level.txt
maestro-1.0.0.dist-info/RECORD
