Metadata-Version: 2.2
Name: maestro
Version: 1.0.0
Summary: Streamline the fine-tuning process for vision-language models like PaliGemma 2, Florence-2, and Qwen2.5-VL.
Author-email: Piotr Skalski <piotr.skalski92@gmail.com>
Maintainer-email: Piotr Skalski <piotr.skalski92@gmail.com>
License:                                  Apache License
Project-URL: Homepage, https://roboflow.github.io/multimodal-maestro/
Project-URL: Documentation, https://roboflow.github.io/multimodal-maestro/
Project-URL: Repository, https://github.com/roboflow/multimodal-maestro
Project-URL: Issues, https://github.com/roboflow/multimodal-maestro/issues
Project-URL: Changelog, https://github.com/roboflow/multimodal-maestro/blob/main/CHANGELOG.md
Keywords: roboflow,maestro,transformers,torch,accelerate,multimodal,lmm,vision,nlp,prompting,vlm
Classifier: Development Status :: 3 - Alpha
Classifier: Intended Audience :: Developers
Classifier: Intended Audience :: Education
Classifier: Intended Audience :: Science/Research
Classifier: License :: OSI Approved :: Apache Software License
Classifier: Programming Language :: Python :: 3
Classifier: Programming Language :: Python :: 3.9
Classifier: Programming Language :: Python :: 3.10
Classifier: Programming Language :: Python :: 3.11
Classifier: Programming Language :: Python :: 3.12
Classifier: Topic :: Software Development
Classifier: Topic :: Scientific/Engineering
Classifier: Topic :: Scientific/Engineering :: Artificial Intelligence
Classifier: Typing :: Typed
Classifier: Operating System :: Microsoft :: Windows
Classifier: Operating System :: POSIX :: Linux
Classifier: Operating System :: MacOS
Requires-Python: <3.13,>=3.9
License-File: LICENSE
Requires-Dist: dacite>=1.9.1
Requires-Dist: lightning>=2.4.0
Requires-Dist: supervision<0.26.0,>=0.20.0
Requires-Dist: requests<=2.32.3,>=2.31.0
Requires-Dist: typer>=0.12.5
Requires-Dist: evaluate>=0.4.3
Requires-Dist: nltk>=3.9.0
Requires-Dist: sacrebleu>=2.3.0
Requires-Dist: pillow>=9.4
Provides-Extra: docs
Requires-Dist: mkdocs-material[imaging]<9.7.0,>=9.5.35; extra == "docs"
Requires-Dist: mkdocstrings[python]<0.28.1,>=0.20.0; extra == "docs"
Requires-Dist: mike~=2.1.3; extra == "docs"
Provides-Extra: dev
Requires-Dist: pytest~=8.3.2; extra == "dev"
Requires-Dist: pre-commit<4.2,>=3.8; extra == "dev"
Requires-Dist: mypy<1.15.0,>=1.11.2; extra == "dev"
Requires-Dist: ruff<0.10.0,>=0.6.5; extra == "dev"
Requires-Dist: tox<4.25.0,>=4.18.1; extra == "dev"
Provides-Extra: florence-2
Requires-Dist: peft>=0.12; extra == "florence-2"
Requires-Dist: transformers>=4.43.0; extra == "florence-2"
Requires-Dist: torch>=2.4.0; extra == "florence-2"
Requires-Dist: flash-attn>=2.7.0.post2; sys_platform != "darwin" and extra == "florence-2"
Provides-Extra: paligemma-2
Requires-Dist: peft>=0.12; extra == "paligemma-2"
Requires-Dist: torch>=2.4.0; extra == "paligemma-2"
Requires-Dist: transformers<4.48.0; extra == "paligemma-2"
Requires-Dist: bitsandbytes>=0.45.0; extra == "paligemma-2"
Provides-Extra: qwen-2-5-vl
Requires-Dist: accelerate>=1.2.1; extra == "qwen-2-5-vl"
Requires-Dist: peft>=0.12; extra == "qwen-2-5-vl"
Requires-Dist: torch>=2.4.0; extra == "qwen-2-5-vl"
Requires-Dist: torchvision>=0.20.0; extra == "qwen-2-5-vl"
Requires-Dist: bitsandbytes>=0.45.0; extra == "qwen-2-5-vl"
Requires-Dist: qwen-vl-utils>=0.0.8; extra == "qwen-2-5-vl"
